azure/purview/administration/__init__.py
azure/purview/administration/_version.py
azure/purview/administration/account/__init__.py
azure/purview/administration/account/_configuration.py
azure/purview/administration/account/_purview_account_client.py
azure/purview/administration/account/_vendor.py
azure/purview/administration/account/_version.py
azure/purview/administration/account/aio/__init__.py
azure/purview/administration/account/aio/_configuration.py
azure/purview/administration/account/aio/_purview_account_client.py
azure/purview/administration/account/aio/operations/__init__.py
azure/purview/administration/account/aio/operations/_operations.py
azure/purview/administration/account/operations/__init__.py
azure/purview/administration/account/operations/_operations.py
azure/purview/administration/metadatapolicies/__init__.py
azure/purview/administration/metadatapolicies/_configuration.py
azure/purview/administration/metadatapolicies/_purview_metadata_policies_client.py
azure/purview/administration/metadatapolicies/_vendor.py
azure/purview/administration/metadatapolicies/_version.py
azure/purview/administration/metadatapolicies/aio/__init__.py
azure/purview/administration/metadatapolicies/aio/_configuration.py
azure/purview/administration/metadatapolicies/aio/_purview_metadata_policies_client.py
azure/purview/administration/metadatapolicies/aio/operations/__init__.py
azure/purview/administration/metadatapolicies/aio/operations/_operations.py
azure/purview/administration/metadatapolicies/operations/__init__.py
azure/purview/administration/metadatapolicies/operations/_operations.py
azure_purview_administration-1.0.0b1.dist-info/METADATA
azure_purview_administration-1.0.0b1.dist-info/WHEEL
azure_purview_administration-1.0.0b1.dist-info/top_level.txt
azure_purview_administration-1.0.0b1.dist-info/RECORD
