Metadata-Version: 2.1
Name: azure-purview-administration
Version: 1.0.0b1
Summary: Microsoft Azure Purview Administration Client Library for Python
Home-page: https://github.com/Azure/azure-sdk-for-python
Author: Microsoft Corporation
Author-email: azpysdkhelp@microsoft.com
License: MIT License
Platform: UNKNOWN
Classifier: Development Status :: 4 - Beta
Classifier: Programming Language :: Python
Classifier: Programming Language :: Python :: 2
Classifier: Programming Language :: Python :: 2.7
Classifier: Programming Language :: Python :: 3
Classifier: Programming Language :: Python :: 3.6
Classifier: Programming Language :: Python :: 3.7
Classifier: Programming Language :: Python :: 3.8
Classifier: Programming Language :: Python :: 3.9
Classifier: Programming Language :: Python :: 3.10
Classifier: License :: OSI Approved :: MIT License
Requires-Dist: azure-core (<2.0.0,>=1.18.0)
Requires-Dist: msrest (>=0.6.21)
Requires-Dist: six (>=1.11.0)
Requires-Dist: azure-purview-nspkg ; python_version<'3.0'
Requires-Dist: typing ; python_version<'3.5'
